jk_cmdoutputparsinghelper/CharMatrix.py
jk_cmdoutputparsinghelper/ColumnDef.py
jk_cmdoutputparsinghelper/LineList.py
jk_cmdoutputparsinghelper/LineParser_ParseAtFirstDelimiter.py
jk_cmdoutputparsinghelper/SpaceInfoSequence.py
jk_cmdoutputparsinghelper/StrNode.py
jk_cmdoutputparsinghelper/Table.py
jk_cmdoutputparsinghelper/TextData.py
jk_cmdoutputparsinghelper/TextSpanInfo.py
jk_cmdoutputparsinghelper/TextSpanInfoSequence.py
jk_cmdoutputparsinghelper/ValueParserDef.py
jk_cmdoutputparsinghelper/ValueParser_ByteWithUnit.py
jk_cmdoutputparsinghelper/_LineUtils.py
jk_cmdoutputparsinghelper/__init__.py
jk_cmdoutputparsinghelper-0.2025.8.24.dist-info/licenses/LICENSE.txt
jk_cmdoutputparsinghelper-0.2025.8.24.dist-info/WHEEL
jk_cmdoutputparsinghelper-0.2025.8.24.dist-info/METADATA
jk_cmdoutputparsinghelper-0.2025.8.24.dist-info/RECORD
