Metadata-Version: 2.4
Name: jk_cmdoutputparsinghelper
Version: 0.2025.8.24
Summary: Assists in parsing output of *nix system commands such as df, systemctrl and others.
Keywords: 
Author-email: Jürgen Knauth <pubsrc@binary-overflow.de>
Maintainer-email: Jürgen Knauth <pubsrc@binary-overflow.de>
Requires-Python: >=3.8
Classifier: Development Status :: 3 - Alpha
Classifier: Programming Language :: Python :: 3
Classifier: License :: OSI Approved :: Apache Software License
License-File: LICENSE.txt
Requires-Dist: jk_typing
Requires-Dist: jk_prettyprintobj
Requires-Dist: jk_typing
